Workbook

Sheet Data_Audit
A1: RETAILPULSE BI — DATA QUALITY AUDIT
A2: Raw rows loaded: 862 | Clean rows after audit: 831 | Rows removed: 31
A4: Check | B4: Result (rows found) | C4: Action Taken | D4: Notes
A5: Duplicate Orders | B5: 12 | C5: Removed | D5: Exact duplicate rows dropped, first occurrence kept
A6: Missing Product IDs | B6: 8 | C6: Removed | D6: Cannot map to a product; excluded from analysis
A7: Missing Order Dates | B7: 5 | C7: Removed | D7: Cannot be placed on a time trend; excluded
A8: Invalid Quantity (<=0) | B8: 6 | C8: Removed | D8: Negative/zero quantity is not a valid sale
A9: Missing Region | B9: 6 | C9: Handled | D9: Filled as 'Unknown' region/state, row kept
A10: Invalid Discount (<0 or >90%) | B10: 4 | C10: Corrected | D10: Clipped to a valid 0%-90% range
A11: Missing Customer ID | B11: 5 | C11: Handled | D11: Filled as 'Unknown Customer', row kept
A13: Conclusion
A14: The raw export contained duplicate transactions, missing keys and a few invalid values. After the audit, the dataset is reliable enough for revenue and profit analysis. The cleaned data lives in the 'Orders_Clean' sheet and is the single source used everywhere else in this workbook.

Sheet Orders_Clean
A1: Order_ID | B1: Order_Date | C1: Customer_ID | D1: Product_ID | E1: Product_Name | F1: Category | G1: Region | H1: State | I1: Sales_Channel | J1: Quantity | K1: Unit_Price | L1: Discount | M1: Cost | N1: Revenue | O1: Profit | P1: Profit_Margin | Q1: Month | R1: Year_Month
A2: ORD-100722 | B2: 2024-07-08 | C2: CUST-1045 | D2: P-5009 | E2: Non-Stick Pan | F2: Home & Kitchen | G2: West | H2: Goa | I2: Online | J2: 6 | K2: 4349 | L2: 0.25 | M2: 14932.62 | N2: =J2*K2*(1-L2) -> 19570.5 | O2: =N2-M2 -> 4637.88 | P2: =IFERROR(O2/N2,0) -> 0.23698321 | Q2: =TEXT(B2,"mmm") -> Jul | R2: =TEXT(B2,"yyyy-mm") -> 2024-07
A3: ORD-100729 | B3: 2024-12-02 | C3: CUST-1051 | D3: P-5004 | E3: Power Bank | F3: Electronics | G3: West | H3: Maharashtra | I3: Online | J3: 4 | K3: 2850 | L3: 0.1 | M3: 8512.6 | N3: =J3*K3*(1-L3) -> 10260 | O3: =N3-M3 -> 1747.4 | P3: =IFERROR(O3/N3,0) -> 0.17031189 | Q3: =TEXT(B3,"mmm") -> Dec | R3: =TEXT(B3,"yyyy-mm") -> 2024-12
A4: ORD-100410 | B4: 2024-06-27 | C4: CUST-1036 | D4: P-5017 | E4: Men's T-Shirt | F4: Fashion | G4: North | H4: Delhi | I4: Online | J4: 3 | K4: 7079 | L4: 0.1 | M4: 8219.34 | N4: =J4*K4*(1-L4) -> 19113.3 | O4: =N4-M4 -> 10893.96 | P4: =IFERROR(O4/N4,0) -> 0.56996751 | Q4: =TEXT(B4,"mmm") -> Jun | R4: =TEXT(B4,"yyyy-mm") -> 2024-06
A5: ORD-100472 | B5: 2024-12-28 | C5: CUST-1003 | D5: P-5039 | E5: Skipping Rope | F5: Sports & Fitness | G5: South | H5: Karnataka | I5: Store | J5: 3 | K5: 3059 | L5: 0 | M5: 4819.38 | N5: =J5*K5*(1-L5) -> 9177 | O5: =N5-M5 -> 4357.62 | P5: =IFERROR(O5/N5,0) -> 0.47484145 | Q5: =TEXT(B5,"mmm") -> Dec | R5: =TEXT(B5,"yyyy-mm") -> 2024-12
A6: ORD-100081 | B6: 2024-11-27 | C6: CUST-1129 | D6: P-5038 | E6: Cycling Helmet | F6: Sports & Fitness | G6: East | H6: West Bengal | I6: Online | J6: 5 | K6: 4769 | L6: 0.15 | M6: 13624.05 | N6: =J6*K6*(1-L6) -> 20268.25 | O6: =N6-M6 -> 6644.2 | P6: =IFERROR(O6/N6,0) -> 0.32781321 | Q6: =TEXT(B6,"mmm") -> Nov | R6: =TEXT(B6,"yyyy-mm") -> 2024-11
A7: ORD-100057 | B7: 2024-04-22 | C7: CUST-1108 | D7: P-5027 | E7: Shampoo | F7: Beauty & Personal Care | G7: North | H7: Delhi | I7: Store | J7: 3 | K7: 3719 | L7: 0 | M7: 4426.11 | N7: =J7*K7*(1-L7) -> 11157 | O7: =N7-M7 -> 6730.89 | P7: =IFERROR(O7/N7,0) -> 0.60328852 | Q7: =TEXT(B7,"mmm") -> Apr | R7: =TEXT(B7,"yyyy-mm") -> 2024-04
A8: ORD-100673 | B8: 2024-12-04 | C8: Unknown Customer | D8: P-5039 | E8: Skipping Rope | F8: Sports & Fitness | G8: West | H8: Goa | I8: Online | J8: 4 | K8: 3059 | L8: 0 | M8: 6425.84 | N8: =J8*K8*(1-L8) -> 12236 | O8: =N8-M8 -> 5810.16 | P8: =IFERROR(O8/N8,0) -> 0.47484145 | Q8: =TEXT(B8,"mmm") -> Dec | R8: =TEXT(B8,"yyyy-mm") -> 2024-12
A9: ORD-100518 | B9: 2024-11-04 | C9: CUST-1059 | D9: P-5015 | E9: Table Lamp | F9: Home & Kitchen | G9: North | H9: Delhi | I9: Online | J9: 6 | K9: 5529 | L9: 0.05 | M9: 18697.56 | N9: =J9*K9*(1-L9) -> 31515.3 | O9: =N9-M9 -> 12817.74 | P9: =IFERROR(O9/N9,0) -> 0.40671483 | Q9: =TEXT(B9,"mmm") -> Nov | R9: =TEXT(B9,"yyyy-mm") -> 2024-11
A10: ORD-100719 | B10: 2024-06-10 | C10: CUST-1176 | D10: P-5038 | E10: Cycling Helmet | F10: Sports & Fitness | G10: West | H10: Gujarat | I10: Online | J10: 4 | K10: 4769 | L10: 0.2 | M10: 10899.24 | N10: =J10*K10*(1-L10) -> 15260.8 | O10: =N10-M10 -> 4361.56 | P10: =IFERROR(O10/N10,0) -> 0.28580153 | Q10: =TEXT(B10,"mmm") -> Jun | R10: =TEXT(B10,"yyyy-mm") -> 2024-06
A11: ORD-100735 | B11: 2024-07-27 | C11: CUST-1044 | D11: P-5010 | E11: Air Fryer | F11: Home & Kitchen | G11: North | H11: Punjab | I11: Online | J11: 2 | K11: 2000 | L11: 0 | M11: 1742.6 | N11: =J11*K11*(1-L11) -> 4000 | O11: =N11-M11 -> 2257.4 | P11: =IFERROR(O11/N11,0) -> 0.56435 | Q11: =TEXT(B11,"mmm") -> Jul | R11: =TEXT(B11,"yyyy-mm") -> 2024-07
A12: ORD-100572 | B12: 2024-06-27 | C12: CUST-1096 | D12: P-5017 | E12: Men's T-Shirt | F12: Fashion | G12: East | H12: Assam | I12: Online | J12: 2 | K12: 7079 | L12: 0.25 | M12: 5479.56 | N12: =J12*K12*(1-L12) -> 10618.5 | O12: =N12-M12 -> 5138.94 | P12: =IFERROR(O12/N12,0) -> 0.48396101 | Q12: =TEXT(B12,"mmm") -> Jun | R12: =TEXT(B12,"yyyy-mm") -> 2024-06
A13: ORD-100126 | B13: 2024-11-02 | C13: CUST-1048 | D13: P-5001 | E13: Wireless Earbuds | F13: Electronics | G13: South | H13: Kerala | I13: Store | J13: 10 | K13: 3069 | L13: 0 | M13: 22920.8 | N13: =J13*K13*(1-L13) -> 30690 | O13: =N13-M13 -> 7769.2 | P13: =IFERROR(O13/N13,0) -> 0.25315086 | Q13: =TEXT(B13,"mmm") -> Nov | R13: =TEXT(B13,"yyyy-mm") -> 2024-11
... A832: ORD-100452 | B832: 2024-10-30 | C832: CUST-1033 | D832: P-5034 | E832: Dumbbell Set | F832: Sports & Fitness | G832: West | H832: Maharashtra | I832: Online | J832: 6 | K832: 3969 | L832: 0.05 | M832: 12887.82 | N832: =J832*K832*(1-L832) -> 22623.3 | O832: =N832-M832 -> 9735.48 | P832: =IFERROR(O832/N832,0) -> 0.43032979 | Q832: =TEXT(B832,"mmm") -> Oct | R832: =TEXT(B832,"yyyy-mm") -> 2024-10

Sheet KPI_Summary
A1: RETAILPULSE BI — KPI SUMMARY
A3: KPI | B3: Value
A4: Total Revenue | B4: =SUM(Orders_Clean!$N$2:$N$832) -> 11444763
A5: Total Profit | B5: =SUM(Orders_Clean!$O$2:$O$832) -> 4567009.3
A6: Total Orders | B6: =COUNTA(Orders_Clean!$A$2:$A$832) -> 831
A7: Total Units Sold | B7: =SUM(Orders_Clean!$J$2:$J$832) -> 3440
A8: Average Order Value | B8: =B4/B6 -> 13772.278
A9: Overall Profit Margin | B9: =B5/B4 -> 0.39904796

Sheet Category_Analysis
A1: RETAILPULSE BI — CATEGORY ANALYSIS
A3: Category | B3: Revenue | C3: Profit | D3: Profit Margin | E3: Units Sold
A4: Beauty & Personal Care | B4: =SUMIF(Orders_Clean!$F$2:$F$832,A4,Orders_Clean!$N$2:$N$832) -> 2298901.7 | C4: =SUMIF(Orders_Clean!$F$2:$F$832,A4,Orders_Clean!$O$2:$O$832) -> 806720.57 | D4: =IFERROR(C4/B4,0) -> 0.35091564 | E4: =SUMIF(Orders_Clean!$F$2:$F$832,A4,Orders_Clean!$J$2:$J$832) -> 720
A5: Electronics | B5: =SUMIF(Orders_Clean!$F$2:$F$832,A5,Orders_Clean!$N$2:$N$832) -> 1921388.4 | C5: =SUMIF(Orders_Clean!$F$2:$F$832,A5,Orders_Clean!$O$2:$O$832) -> 673445.68 | D5: =IFERROR(C5/B5,0) -> 0.3504995 | E5: =SUMIF(Orders_Clean!$F$2:$F$832,A5,Orders_Clean!$J$2:$J$832) -> 655
A6: Fashion | B6: =SUMIF(Orders_Clean!$F$2:$F$832,A6,Orders_Clean!$N$2:$N$832) -> 2278983.6 | C6: =SUMIF(Orders_Clean!$F$2:$F$832,A6,Orders_Clean!$O$2:$O$832) -> 1015170.9 | D6: =IFERROR(C6/B6,0) -> 0.44544896 | E6: =SUMIF(Orders_Clean!$F$2:$F$832,A6,Orders_Clean!$J$2:$J$832) -> 725
A7: Home & Kitchen | B7: =SUMIF(Orders_Clean!$F$2:$F$832,A7,Orders_Clean!$N$2:$N$832) -> 1938977.9 | C7: =SUMIF(Orders_Clean!$F$2:$F$832,A7,Orders_Clean!$O$2:$O$832) -> 841128.21 | D7: =IFERROR(C7/B7,0) -> 0.4337998 | E7: =SUMIF(Orders_Clean!$F$2:$F$832,A7,Orders_Clean!$J$2:$J$832) -> 646
A8: Sports & Fitness | B8: =SUMIF(Orders_Clean!$F$2:$F$832,A8,Orders_Clean!$N$2:$N$832) -> 3006511.5 | C8: =SUMIF(Orders_Clean!$F$2:$F$832,A8,Orders_Clean!$O$2:$O$832) -> 1230544 | D8: =IFERROR(C8/B8,0) -> 0.40929296 | E8: =SUMIF(Orders_Clean!$F$2:$F$832,A8,Orders_Clean!$J$2:$J$832) -> 694

Sheet Regional_Analysis
A1: RETAILPULSE BI — REGIONAL ANALYSIS
A3: Region | B3: Revenue | C3: Profit | D3: Profit Margin | E3: Units Sold
A4: East | B4: =SUMIF(Orders_Clean!$G$2:$G$832,A4,Orders_Clean!$N$2:$N$832) -> 2876056 | C4: =SUMIF(Orders_Clean!$G$2:$G$832,A4,Orders_Clean!$O$2:$O$832) -> 1200664.9 | D4: =IFERROR(C4/B4,0) -> 0.41746922 | E4: =SUMIF(Orders_Clean!$G$2:$G$832,A4,Orders_Clean!$J$2:$J$832) -> 836
A5: North | B5: =SUMIF(Orders_Clean!$G$2:$G$832,A5,Orders_Clean!$N$2:$N$832) -> 2492916.2 | C5: =SUMIF(Orders_Clean!$G$2:$G$832,A5,Orders_Clean!$O$2:$O$832) -> 978532.16 | D5: =IFERROR(C5/B5,0) -> 0.39252508 | E5: =SUMIF(Orders_Clean!$G$2:$G$832,A5,Orders_Clean!$J$2:$J$832) -> 768
A6: South | B6: =SUMIF(Orders_Clean!$G$2:$G$832,A6,Orders_Clean!$N$2:$N$832) -> 3011318.8 | C6: =SUMIF(Orders_Clean!$G$2:$G$832,A6,Orders_Clean!$O$2:$O$832) -> 1227124.7 | D6: =IFERROR(C6/B6,0) -> 0.40750407 | E6: =SUMIF(Orders_Clean!$G$2:$G$832,A6,Orders_Clean!$J$2:$J$832) -> 913
A7: Unknown | B7: =SUMIF(Orders_Clean!$G$2:$G$832,A7,Orders_Clean!$N$2:$N$832) -> 60644.9 | C7: =SUMIF(Orders_Clean!$G$2:$G$832,A7,Orders_Clean!$O$2:$O$832) -> 29397.42 | D7: =IFERROR(C7/B7,0) -> 0.48474678 | E7: =SUMIF(Orders_Clean!$G$2:$G$832,A7,Orders_Clean!$J$2:$J$832) -> 19
A8: West | B8: =SUMIF(Orders_Clean!$G$2:$G$832,A8,Orders_Clean!$N$2:$N$832) -> 3003827.1 | C8: =SUMIF(Orders_Clean!$G$2:$G$832,A8,Orders_Clean!$O$2:$O$832) -> 1131290.2 | D8: =IFERROR(C8/B8,0) -> 0.37661629 | E8: =SUMIF(Orders_Clean!$G$2:$G$832,A8,Orders_Clean!$J$2:$J$832) -> 904

Sheet Product_Analysis
A1: RETAILPULSE BI — PRODUCT ANALYSIS
A3: TOP 10 PRODUCTS BY REVENUE
A4: Product Name | B4: Revenue | C4: Profit | D4: Profit Margin | E4: Units Sold
A5: Men's T-Shirt | B5: =SUMIF(Orders_Clean!$E$2:$E$832,A5,Orders_Clean!$N$2:$N$832) -> 739755.5 | C5: =SUMIF(Orders_Clean!$E$2:$E$832,A5,Orders_Clean!$O$2:$O$832) -> 427420.58 | D5: =IFERROR(C5/B5,0) -> 0.57778628 | E5: =SUMIF(Orders_Clean!$E$2:$E$832,A5,Orders_Clean!$J$2:$J$832) -> 114
A6: Gym Bag | B6: =SUMIF(Orders_Clean!$E$2:$E$832,A6,Orders_Clean!$N$2:$N$832) -> 694717.05 | C6: =SUMIF(Orders_Clean!$E$2:$E$832,A6,Orders_Clean!$O$2:$O$832) -> 350728.22 | D6: =IFERROR(C6/B6,0) -> 0.50485046 | E6: =SUMIF(Orders_Clean!$E$2:$E$832,A6,Orders_Clean!$J$2:$J$832) -> 101
A7: Trimmer | B7: =SUMIF(Orders_Clean!$E$2:$E$832,A7,Orders_Clean!$N$2:$N$832) -> 625758.1 | C7: =SUMIF(Orders_Clean!$E$2:$E$832,A7,Orders_Clean!$O$2:$O$832) -> 143994.58 | D7: =IFERROR(C7/B7,0) -> 0.23011221 | E7: =SUMIF(Orders_Clean!$E$2:$E$832,A7,Orders_Clean!$J$2:$J$832) -> 138
A8: Football | B8: =SUMIF(Orders_Clean!$E$2:$E$832,A8,Orders_Clean!$N$2:$N$832) -> 511563.15 | C8: =SUMIF(Orders_Clean!$E$2:$E$832,A8,Orders_Clean!$O$2:$O$832) -> 236551.66 | D8: =IFERROR(C8/B8,0) -> 0.4624095 | E8: =SUMIF(Orders_Clean!$E$2:$E$832,A8,Orders_Clean!$J$2:$J$832) -> 113
A9: Lipstick Set | B9: =SUMIF(Orders_Clean!$E$2:$E$832,A9,Orders_Clean!$N$2:$N$832) -> 450721.6 | C9: =SUMIF(Orders_Clean!$E$2:$E$832,A9,Orders_Clean!$O$2:$O$832) -> 166527.7 | D9: =IFERROR(C9/B9,0) -> 0.36946909 | E9: =SUMIF(Orders_Clean!$E$2:$E$832,A9,Orders_Clean!$J$2:$J$832) -> 90
A10: LED Monitor | B10: =SUMIF(Orders_Clean!$E$2:$E$832,A10,Orders_Clean!$N$2:$N$832) -> 442300.95 | C10: =SUMIF(Orders_Clean!$E$2:$E$832,A10,Orders_Clean!$O$2:$O$832) -> 231163.27 | D10: =IFERROR(C10/B10,0) -> 0.52263797 | E10: =SUMIF(Orders_Clean!$E$2:$E$832,A10,Orders_Clean!$J$2:$J$832) -> 104
A11: Resistance Bands | B11: =SUMIF(Orders_Clean!$E$2:$E$832,A11,Orders_Clean!$N$2:$N$832) -> 438961.05 | C11: =SUMIF(Orders_Clean!$E$2:$E$832,A11,Orders_Clean!$O$2:$O$832) -> 187896.33 | D11: =IFERROR(C11/B11,0) -> 0.42804784 | E11: =SUMIF(Orders_Clean!$E$2:$E$832,A11,Orders_Clean!$J$2:$J$832) -> 72
A12: Non-Stick Pan | B12: =SUMIF(Orders_Clean!$E$2:$E$832,A12,Orders_Clean!$N$2:$N$832) -> 426854.35 | C12: =SUMIF(Orders_Clean!$E$2:$E$832,A12,Orders_Clean!$O$2:$O$832) -> 163044.73 | D12: =IFERROR(C12/B12,0) -> 0.38196806 | E12: =SUMIF(Orders_Clean!$E$2:$E$832,A12,Orders_Clean!$J$2:$J$832) -> 106
A13: Women's Kurti | B13: =SUMIF(Orders_Clean!$E$2:$E$832,A13,Orders_Clean!$N$2:$N$832) -> 426285.9 | C13: =SUMIF(Orders_Clean!$E$2:$E$832,A13,Orders_Clean!$O$2:$O$832) -> 172910.14 | D13: =IFERROR(C13/B13,0) -> 0.40562012 | E13: =SUMIF(Orders_Clean!$E$2:$E$832,A13,Orders_Clean!$J$2:$J$832) -> 83
A14: Dumbbell Set | B14: =SUMIF(Orders_Clean!$E$2:$E$832,A14,Orders_Clean!$N$2:$N$832) -> 425476.8 | C14: =SUMIF(Orders_Clean!$E$2:$E$832,A14,Orders_Clean!$O$2:$O$832) -> 178460.25 | D14: =IFERROR(C14/B14,0) -> 0.41943591 | E14: =SUMIF(Orders_Clean!$E$2:$E$832,A14,Orders_Clean!$J$2:$J$832) -> 115
A16: TOP 10 PRODUCTS BY PROFIT
A17: Product Name | B17: Revenue | C17: Profit | D17: Profit Margin | E17: Units Sold
A18: Men's T-Shirt | B18: =SUMIF(Orders_Clean!$E$2:$E$832,A18,Orders_Clean!$N$2:$N$832) -> 739755.5 | C18: =SUMIF(Orders_Clean!$E$2:$E$832,A18,Orders_Clean!$O$2:$O$832) -> 427420.58 | D18: =IFERROR(C18/B18,0) -> 0.57778628 | E18: =SUMIF(Orders_Clean!$E$2:$E$832,A18,Orders_Clean!$J$2:$J$832) -> 114
A19: Gym Bag | B19: =SUMIF(Orders_Clean!$E$2:$E$832,A19,Orders_Clean!$N$2:$N$832) -> 694717.05 | C19: =SUMIF(Orders_Clean!$E$2:$E$832,A19,Orders_Clean!$O$2:$O$832) -> 350728.22 | D19: =IFERROR(C19/B19,0) -> 0.50485046 | E19: =SUMIF(Orders_Clean!$E$2:$E$832,A19,Orders_Clean!$J$2:$J$832) -> 101
A20: Football | B20: =SUMIF(Orders_Clean!$E$2:$E$832,A20,Orders_Clean!$N$2:$N$832) -> 511563.15 | C20: =SUMIF(Orders_Clean!$E$2:$E$832,A20,Orders_Clean!$O$2:$O$832) -> 236551.66 | D20: =IFERROR(C20/B20,0) -> 0.4624095 | E20: =SUMIF(Orders_Clean!$E$2:$E$832,A20,Orders_Clean!$J$2:$J$832) -> 113
A21: LED Monitor | B21: =SUMIF(Orders_Clean!$E$2:$E$832,A21,Orders_Clean!$N$2:$N$832) -> 442300.95 | C21: =SUMIF(Orders_Clean!$E$2:$E$832,A21,Orders_Clean!$O$2:$O$832) -> 231163.27 | D21: =IFERROR(C21/B21,0) -> 0.52263797 | E21: =SUMIF(Orders_Clean!$E$2:$E$832,A21,Orders_Clean!$J$2:$J$832) -> 104
A22: Blender | B22: =SUMIF(Orders_Clean!$E$2:$E$832,A22,Orders_Clean!$N$2:$N$832) -> 422218 | C22: =SUMIF(Orders_Clean!$E$2:$E$832,A22,Orders_Clean!$O$2:$O$832) -> 222349.84 | D22: =IFERROR(C22/B22,0) -> 0.52662331 | E22: =SUMIF(Orders_Clean!$E$2:$E$832,A22,Orders_Clean!$J$2:$J$832) -> 92
A23: Resistance Bands | B23: =SUMIF(Orders_Clean!$E$2:$E$832,A23,Orders_Clean!$N$2:$N$832) -> 438961.05 | C23: =SUMIF(Orders_Clean!$E$2:$E$832,A23,Orders_Clean!$O$2:$O$832) -> 187896.33 | D23: =IFERROR(C23/B23,0) -> 0.42804784 | E23: =SUMIF(Orders_Clean!$E$2:$E$832,A23,Orders_Clean!$J$2:$J$832) -> 72
A24: Dinner Set | B24: =SUMIF(Orders_Clean!$E$2:$E$832,A24,Orders_Clean!$N$2:$N$832) -> 317457 | C24: =SUMIF(Orders_Clean!$E$2:$E$832,A24,Orders_Clean!$O$2:$O$832) -> 183158.16 | D24: =IFERROR(C24/B24,0) -> 0.57695423 | E24: =SUMIF(Orders_Clean!$E$2:$E$832,A24,Orders_Clean!$J$2:$J$832) -> 69
A25: Dumbbell Set | B25: =SUMIF(Orders_Clean!$E$2:$E$832,A25,Orders_Clean!$N$2:$N$832) -> 425476.8 | C25: =SUMIF(Orders_Clean!$E$2:$E$832,A25,Orders_Clean!$O$2:$O$832) -> 178460.25 | D25: =IFERROR(C25/B25,0) -> 0.41943591 | E25: =SUMIF(Orders_Clean!$E$2:$E$832,A25,Orders_Clean!$J$2:$J$832) -> 115
A26: Perfume | B26: =SUMIF(Orders_Clean!$E$2:$E$832,A26,Orders_Clean!$N$2:$N$832) -> 340939.55 | C26: =SUMIF(Orders_Clean!$E$2:$E$832,A26,Orders_Clean!$O$2:$O$832) -> 174716.1 | D26: =IFERROR(C26/B26,0) -> 0.51245477 | E26: =SUMIF(Orders_Clean!$E$2:$E$832,A26,Orders_Clean!$J$2:$J$832) -> 85
A27: Women's Kurti | B27: =SUMIF(Orders_Clean!$E$2:$E$832,A27,Orders_Clean!$N$2:$N$832) -> 426285.9 | C27: =SUMIF(Orders_Clean!$E$2:$E$832,A27,Orders_Clean!$O$2:$O$832) -> 172910.14 | D27: =IFERROR(C27/B27,0) -> 0.40562012 | E27: =SUMIF(Orders_Clean!$E$2:$E$832,A27,Orders_Clean!$J$2:$J$832) -> 83
A29: BOTTOM 10 PRODUCTS BY REVENUE (LOW PERFORMERS)
A30: Product Name | B30: Revenue | C30: Profit | D30: Profit Margin | E30: Units Sold
A31: Yoga Mat | B31: =SUMIF(Orders_Clean!$E$2:$E$832,A31,Orders_Clean!$N$2:$N$832) -> 33305.75 | C31: =SUMIF(Orders_Clean!$E$2:$E$832,A31,Orders_Clean!$O$2:$O$832) -> 9473.03 | D31: =IFERROR(C31/B31,0) -> 0.28442626 | E31: =SUMIF(Orders_Clean!$E$2:$E$832,A31,Orders_Clean!$J$2:$J$832) -> 36
A32: Storage Containers | B32: =SUMIF(Orders_Clean!$E$2:$E$832,A32,Orders_Clean!$N$2:$N$832) -> 43785.2 | C32: =SUMIF(Orders_Clean!$E$2:$E$832,A32,Orders_Clean!$O$2:$O$832) -> 17290.48 | D32: =IFERROR(C32/B32,0) -> 0.39489325 | E32: =SUMIF(Orders_Clean!$E$2:$E$832,A32,Orders_Clean!$J$2:$J$832) -> 64
A33: Sunscreen | B33: =SUMIF(Orders_Clean!$E$2:$E$832,A33,Orders_Clean!$N$2:$N$832) -> 55738 | C33: =SUMIF(Orders_Clean!$E$2:$E$832,A33,Orders_Clean!$O$2:$O$832) -> 9373.9 | D33: =IFERROR(C33/B33,0) -> 0.1681779 | E33: =SUMIF(Orders_Clean!$E$2:$E$832,A33,Orders_Clean!$J$2:$J$832) -> 102
A34: Coffee Maker | B34: =SUMIF(Orders_Clean!$E$2:$E$832,A34,Orders_Clean!$N$2:$N$832) -> 65285.85 | C34: =SUMIF(Orders_Clean!$E$2:$E$832,A34,Orders_Clean!$O$2:$O$832) -> 14608.85 | D34: =IFERROR(C34/B34,0) -> 0.22376748 | E34: =SUMIF(Orders_Clean!$E$2:$E$832,A34,Orders_Clean!$J$2:$J$832) -> 110
A35: Hair Dryer | B35: =SUMIF(Orders_Clean!$E$2:$E$832,A35,Orders_Clean!$N$2:$N$832) -> 73573.5 | C35: =SUMIF(Orders_Clean!$E$2:$E$832,A35,Orders_Clean!$O$2:$O$832) -> 23912.52 | D35: =IFERROR(C35/B35,0) -> 0.32501539 | E35: =SUMIF(Orders_Clean!$E$2:$E$832,A35,Orders_Clean!$J$2:$J$832) -> 79
A36: Bluetooth Speaker | B36: =SUMIF(Orders_Clean!$E$2:$E$832,A36,Orders_Clean!$N$2:$N$832) -> 99144 | C36: =SUMIF(Orders_Clean!$E$2:$E$832,A36,Orders_Clean!$O$2:$O$832) -> 26364.75 | D36: =IFERROR(C36/B36,0) -> 0.26592381 | E36: =SUMIF(Orders_Clean!$E$2:$E$832,A36,Orders_Clean!$J$2:$J$832) -> 75
A37: Smart Watch | B37: =SUMIF(Orders_Clean!$E$2:$E$832,A37,Orders_Clean!$N$2:$N$832) -> 103713.5 | C37: =SUMIF(Orders_Clean!$E$2:$E$832,A37,Orders_Clean!$O$2:$O$832) -> 44590.02 | D37: =IFERROR(C37/B37,0) -> 0.42993458 | E37: =SUMIF(Orders_Clean!$E$2:$E$832,A37,Orders_Clean!$J$2:$J$832) -> 67
A38: Formal Shirt | B38: =SUMIF(Orders_Clean!$E$2:$E$832,A38,Orders_Clean!$N$2:$N$832) -> 106102.55 | C38: =SUMIF(Orders_Clean!$E$2:$E$832,A38,Orders_Clean!$O$2:$O$832) -> 18040.79 | D38: =IFERROR(C38/B38,0) -> 0.17003163 | E38: =SUMIF(Orders_Clean!$E$2:$E$832,A38,Orders_Clean!$J$2:$J$832) -> 96
A39: Sunglasses | B39: =SUMIF(Orders_Clean!$E$2:$E$832,A39,Orders_Clean!$N$2:$N$832) -> 109066.65 | C39: =SUMIF(Orders_Clean!$E$2:$E$832,A39,Orders_Clean!$O$2:$O$832) -> 47695.45 | D39: =IFERROR(C39/B39,0) -> 0.43730554 | E39: =SUMIF(Orders_Clean!$E$2:$E$832,A39,Orders_Clean!$J$2:$J$832) -> 88
A40: Backpack | B40: =SUMIF(Orders_Clean!$E$2:$E$832,A40,Orders_Clean!$N$2:$N$832) -> 142120 | C40: =SUMIF(Orders_Clean!$E$2:$E$832,A40,Orders_Clean!$O$2:$O$832) -> 51777.58 | D40: =IFERROR(C40/B40,0) -> 0.36432297 | E40: =SUMIF(Orders_Clean!$E$2:$E$832,A40,Orders_Clean!$J$2:$J$832) -> 102

Sheet Monthly_Analysis
A1: RETAILPULSE BI — MONTHLY TREND ANALYSIS
A3: Year_Month | B3: Revenue | C3: Profit | D3: Profit Margin | E3: Orders | F3: MoM Revenue Growth
A4: 2024-01 | B4: =SUMIF(Orders_Clean!$R$2:$R$832,A4,Orders_Clean!$N$2:$N$832) -> 1140047.6 | C4: =SUMIF(Orders_Clean!$R$2:$R$832,A4,Orders_Clean!$O$2:$O$832) -> 452473.8 | D4: =IFERROR(C4/B4,0) -> 0.39689027 | E4: =COUNTIF(Orders_Clean!$R$2:$R$832,A4) -> 79
A5: 2024-02 | B5: =SUMIF(Orders_Clean!$R$2:$R$832,A5,Orders_Clean!$N$2:$N$832) -> 683992.8 | C5: =SUMIF(Orders_Clean!$R$2:$R$832,A5,Orders_Clean!$O$2:$O$832) -> 303170.61 | D5: =IFERROR(C5/B5,0) -> 0.44323655 | E5: =COUNTIF(Orders_Clean!$R$2:$R$832,A5) -> 54 | F5: =IFERROR((B5-B4)/B4,0) -> -0.40003137
A6: 2024-03 | B6: =SUMIF(Orders_Clean!$R$2:$R$832,A6,Orders_Clean!$N$2:$N$832) -> 717313.85 | C6: =SUMIF(Orders_Clean!$R$2:$R$832,A6,Orders_Clean!$O$2:$O$832) -> 286467.1 | D6: =IFERROR(C6/B6,0) -> 0.39936089 | E6: =COUNTIF(Orders_Clean!$R$2:$R$832,A6) -> 65 | F6: =IFERROR((B6-B5)/B5,0) -> 0.048715498
A7: 2024-04 | B7: =SUMIF(Orders_Clean!$R$2:$R$832,A7,Orders_Clean!$N$2:$N$832) -> 894428.6 | C7: =SUMIF(Orders_Clean!$R$2:$R$832,A7,Orders_Clean!$O$2:$O$832) -> 341269.37 | D7: =IFERROR(C7/B7,0) -> 0.38155015 | E7: =COUNTIF(Orders_Clean!$R$2:$R$832,A7) -> 64 | F7: =IFERROR((B7-B6)/B6,0) -> 0.24691389
A8: 2024-05 | B8: =SUMIF(Orders_Clean!$R$2:$R$832,A8,Orders_Clean!$N$2:$N$832) -> 1116329.1 | C8: =SUMIF(Orders_Clean!$R$2:$R$832,A8,Orders_Clean!$O$2:$O$832) -> 427671.22 | D8: =IFERROR(C8/B8,0) -> 0.38310495 | E8: =COUNTIF(Orders_Clean!$R$2:$R$832,A8) -> 81 | F8: =IFERROR((B8-B7)/B7,0) -> 0.24809197
A9: 2024-06 | B9: =SUMIF(Orders_Clean!$R$2:$R$832,A9,Orders_Clean!$N$2:$N$832) -> 482527.9 | C9: =SUMIF(Orders_Clean!$R$2:$R$832,A9,Orders_Clean!$O$2:$O$832) -> 195234.5 | D9: =IFERROR(C9/B9,0) -> 0.40460769 | E9: =COUNTIF(Orders_Clean!$R$2:$R$832,A9) -> 66 | F9: =IFERROR((B9-B8)/B8,0) -> -0.56775481
A10: 2024-07 | B10: =SUMIF(Orders_Clean!$R$2:$R$832,A10,Orders_Clean!$N$2:$N$832) -> 707292.25 | C10: =SUMIF(Orders_Clean!$R$2:$R$832,A10,Orders_Clean!$O$2:$O$832) -> 268481.96 | D10: =IFERROR(C10/B10,0) -> 0.37959127 | E10: =COUNTIF(Orders_Clean!$R$2:$R$832,A10) -> 84 | F10: =IFERROR((B10-B9)/B9,0) -> 0.46580592
A11: 2024-08 | B11: =SUMIF(Orders_Clean!$R$2:$R$832,A11,Orders_Clean!$N$2:$N$832) -> 1001777.4 | C11: =SUMIF(Orders_Clean!$R$2:$R$832,A11,Orders_Clean!$O$2:$O$832) -> 373029.84 | D11: =IFERROR(C11/B11,0) -> 0.37236797 | E11: =COUNTIF(Orders_Clean!$R$2:$R$832,A11) -> 74 | F11: =IFERROR((B11-B10)/B10,0) -> 0.41635576
A12: 2024-09 | B12: =SUMIF(Orders_Clean!$R$2:$R$832,A12,Orders_Clean!$N$2:$N$832) -> 899552.5 | C12: =SUMIF(Orders_Clean!$R$2:$R$832,A12,Orders_Clean!$O$2:$O$832) -> 366243.01 | D12: =IFERROR(C12/B12,0) -> 0.40713912 | E12: =COUNTIF(Orders_Clean!$R$2:$R$832,A12) -> 66 | F12: =IFERROR((B12-B11)/B11,0) -> -0.10204357
A13: 2024-10 | B13: =SUMIF(Orders_Clean!$R$2:$R$832,A13,Orders_Clean!$N$2:$N$832) -> 1474655 | C13: =SUMIF(Orders_Clean!$R$2:$R$832,A13,Orders_Clean!$O$2:$O$832) -> 616824.91 | D13: =IFERROR(C13/B13,0) -> 0.41828422 | E13: =COUNTIF(Orders_Clean!$R$2:$R$832,A13) -> 64 | F13: =IFERROR((B13-B12)/B12,0) -> 0.63932066
A14: 2024-11 | B14: =SUMIF(Orders_Clean!$R$2:$R$832,A14,Orders_Clean!$N$2:$N$832) -> 1477039.1 | C14: =SUMIF(Orders_Clean!$R$2:$R$832,A14,Orders_Clean!$O$2:$O$832) -> 595722.02 | D14: =IFERROR(C14/B14,0) -> 0.40332177 | E14: =COUNTIF(Orders_Clean!$R$2:$R$832,A14) -> 65 | F14: =IFERROR((B14-B13)/B13,0) -> 0.0016167171
A15: 2024-12 | B15: =SUMIF(Orders_Clean!$R$2:$R$832,A15,Orders_Clean!$N$2:$N$832) -> 849806.85 | C15: =SUMIF(Orders_Clean!$R$2:$R$832,A15,Orders_Clean!$O$2:$O$832) -> 340420.99 | D15: =IFERROR(C15/B15,0) -> 0.40058631 | E15: =COUNTIF(Orders_Clean!$R$2:$R$832,A15) -> 69 | F15: =IFERROR((B15-B14)/B14,0) -> -0.42465514
A17: Best month by revenue: 2024-11
A18: Weakest month by revenue: 2024-06

Sheet Channel_Customer_Analysis
A1: RETAILPULSE BI — SALES CHANNEL & TOP CUSTOMERS
A3: SALES CHANNEL COMPARISON
A4: Sales_Channel | B4: Revenue | C4: Profit | D4: Orders
A5: Online | B5: =SUMIF(Orders_Clean!$I$2:$I$832,A5,Orders_Clean!$N$2:$N$832) -> 7268522.5 | C5: =SUMIF(Orders_Clean!$I$2:$I$832,A5,Orders_Clean!$O$2:$O$832) -> 2963859.8 | D5: =COUNTIF(Orders_Clean!$I$2:$I$832,A5) -> 527
A6: Store | B6: =SUMIF(Orders_Clean!$I$2:$I$832,A6,Orders_Clean!$N$2:$N$832) -> 4176240.5 | C6: =SUMIF(Orders_Clean!$I$2:$I$832,A6,Orders_Clean!$O$2:$O$832) -> 1603149.5 | D6: =COUNTIF(Orders_Clean!$I$2:$I$832,A6) -> 304
A9: TOP 10 CUSTOMERS BY REVENUE
A10: Customer_ID | B10: Revenue | C10: Profit | D10: Orders
A11: CUST-1087 | B11: =SUMIF(Orders_Clean!$C$2:$C$832,A11,Orders_Clean!$N$2:$N$832) -> 186845.8 | C11: =SUMIF(Orders_Clean!$C$2:$C$832,A11,Orders_Clean!$O$2:$O$832) -> 91516.97 | D11: =COUNTIF(Orders_Clean!$C$2:$C$832,A11) -> 9
A12: CUST-1144 | B12: =SUMIF(Orders_Clean!$C$2:$C$832,A12,Orders_Clean!$N$2:$N$832) -> 176530.25 | C12: =SUMIF(Orders_Clean!$C$2:$C$832,A12,Orders_Clean!$O$2:$O$832) -> 74013.28 | D12: =COUNTIF(Orders_Clean!$C$2:$C$832,A12) -> 8
A13: CUST-1042 | B13: =SUMIF(Orders_Clean!$C$2:$C$832,A13,Orders_Clean!$N$2:$N$832) -> 175950.9 | C13: =SUMIF(Orders_Clean!$C$2:$C$832,A13,Orders_Clean!$O$2:$O$832) -> 65089.63 | D13: =COUNTIF(Orders_Clean!$C$2:$C$832,A13) -> 12
A14: CUST-1174 | B14: =SUMIF(Orders_Clean!$C$2:$C$832,A14,Orders_Clean!$N$2:$N$832) -> 156580.25 | C14: =SUMIF(Orders_Clean!$C$2:$C$832,A14,Orders_Clean!$O$2:$O$832) -> 64822.13 | D14: =COUNTIF(Orders_Clean!$C$2:$C$832,A14) -> 9
A15: CUST-1162 | B15: =SUMIF(Orders_Clean!$C$2:$C$832,A15,Orders_Clean!$N$2:$N$832) -> 150953 | C15: =SUMIF(Orders_Clean!$C$2:$C$832,A15,Orders_Clean!$O$2:$O$832) -> 73937.7 | D15: =COUNTIF(Orders_Clean!$C$2:$C$832,A15) -> 9
A16: CUST-1140 | B16: =SUMIF(Orders_Clean!$C$2:$C$832,A16,Orders_Clean!$N$2:$N$832) -> 149620 | C16: =SUMIF(Orders_Clean!$C$2:$C$832,A16,Orders_Clean!$O$2:$O$832) -> 79451.93 | D16: =COUNTIF(Orders_Clean!$C$2:$C$832,A16) -> 9
A17: CUST-1147 | B17: =SUMIF(Orders_Clean!$C$2:$C$832,A17,Orders_Clean!$N$2:$N$832) -> 144274.85 | C17: =SUMIF(Orders_Clean!$C$2:$C$832,A17,Orders_Clean!$O$2:$O$832) -> 46888.03 | D17: =COUNTIF(Orders_Clean!$C$2:$C$832,A17) -> 6
A18: CUST-1158 | B18: =SUMIF(Orders_Clean!$C$2:$C$832,A18,Orders_Clean!$N$2:$N$832) -> 138295.55 | C18: =SUMIF(Orders_Clean!$C$2:$C$832,A18,Orders_Clean!$O$2:$O$832) -> 58353.49 | D18: =COUNTIF(Orders_Clean!$C$2:$C$832,A18) -> 7
A19: CUST-1080 | B19: =SUMIF(Orders_Clean!$C$2:$C$832,A19,Orders_Clean!$N$2:$N$832) -> 132291.75 | C19: =SUMIF(Orders_Clean!$C$2:$C$832,A19,Orders_Clean!$O$2:$O$832) -> 48183.49 | D19: =COUNTIF(Orders_Clean!$C$2:$C$832,A19) -> 10
A20: CUST-1176 | B20: =SUMIF(Orders_Clean!$C$2:$C$832,A20,Orders_Clean!$N$2:$N$832) -> 130602.9 | C20: =SUMIF(Orders_Clean!$C$2:$C$832,A20,Orders_Clean!$O$2:$O$832) -> 42343.37 | D20: =COUNTIF(Orders_Clean!$C$2:$C$832,A20) -> 9
